c4f/__init__.py
c4f/__main__.py
c4f/_progress.py
c4f/_purifier.py
c4f/cli.py
c4f/config.py
c4f/main.py
c4f/processor/__init__.py
c4f/processor/base.py
c4f/processor/batch_processor.py
c4f/processor/parallel_processor.py
c4f/processor/processor_factory.py
c4f/processor/processor_queue.py
c4f/processor/sequential_processor.py
c4f/py.typed
c4f/ssl_utils.py
c4f/utils.py
commit_for_free-1.1.5.dist-info/entry_points.txt
commit_for_free-1.1.5.dist-info/LICENSE
commit_for_free-1.1.5.dist-info/METADATA
commit_for_free-1.1.5.dist-info/WHEEL
commit_for_free-1.1.5.dist-info/RECORD
