Metadata-Version: 2.3
Name: commit-for-free
Version: 1.1.5
Summary: A sophisticated Git commit message generator that uses AI to create meaningful, conventional commit messages based on your code changes.
License: MIT
Keywords: git,commit,ai,artificial-intelligence,conventional-commits,developer-tools,automation,cli,command-line,productivity,version-control,commit-message,code-quality,workflow,git-tools,semantic-commits,devops,software-development,python-tool,git-automation,commit-history,code-documentation
Author: Alaamer
Author-email: ahmedmuhamed12@gmail.com
Maintainer: Alaamer
Maintainer-email: ahmedmuhamed239@gmail.com
Requires-Python: >=3.11
Classifier: Development Status :: 5 - Production/Stable
Classifier: Environment :: Console
Classifier: Framework :: Pytest
Classifier: Intended Audience :: Developers
Classifier: Intended Audience :: Information Technology
Classifier: Intended Audience :: System Administrators
Classifier: License :: OSI Approved :: MIT License
Classifier: Natural Language :: English
Classifier: Operating System :: MacOS
Classifier: Operating System :: Microsoft :: Windows
Classifier: Operating System :: OS Independent
Classifier: Operating System :: POSIX
Classifier: Programming Language :: Python
Classifier: Programming Language :: Python :: 3
Classifier: Programming Language :: Python :: 3.11
Classifier: Programming Language :: Python :: 3.12
Classifier: Programming Language :: Python :: 3.13
Classifier: Programming Language :: Python :: Implementation :: CPython
Classifier: Topic :: Software Development
Classifier: Topic :: Software Development :: Libraries
Classifier: Topic :: Software Development :: Libraries :: Python Modules
Classifier: Topic :: Software Development :: Quality Assurance
Classifier: Topic :: Software Development :: Version Control
Classifier: Topic :: Software Development :: Version Control :: Git
Classifier: Topic :: Utilities
Classifier: Typing :: Typed
Provides-Extra: monitoring
Requires-Dist: g4f (>=0.5.7.3,<0.6.0.0)
Requires-Dist: rich (>=14.0.0,<15.0.0)
Project-URL: Bug Tracker, https://github.com/alaamer12/c4f/issues
Project-URL: Changelog, https://github.com/alaamer12/c4f/blob/main/CHANGELOG.md
Project-URL: Documentation, https://github.com/alaamer12/c4f
Project-URL: Funding, https://github.com/sponsors/alaamer12
Project-URL: Homepage, https://github.com/alaamer12/c4f
Project-URL: Repository, https://github.com/alaamer12/c4f
Project-URL: Security, https://github.com/alaamer12/c4f/blob/main/SECURITY.md
Project-URL: Source, https://github.com/alaamer12/c4f
